octoprint_prometheus/__init__.py
octoprint_prometheus/gcodeparser.py
octoprint_prometheus/octoprint_prometheus.py
octoprint_prometheus/octoprint_prometheus_plugin.py
octoprint_prometheus/templates/prometheus_settings.jinja2
octoprint_prometheus-1.1.0.dist-info/METADATA
octoprint_prometheus-1.1.0.dist-info/RECORD
octoprint_prometheus-1.1.0.dist-info/WHEEL
octoprint_prometheus-1.1.0.dist-info/entry_points.txt
octoprint_prometheus-1.1.0.dist-info/top_level.txt
