Metadata-Version: 2.1
Name: octoprint-prometheus
Version: 1.1.0
Summary: Prometheus endpoint for OctoPrint
Home-page: https://github.com/sbelectronics/octoprint-prometheus
Author: Scott Baker
Author-email: smbaker@gmail.com
License: AGPLv3
Platform: UNKNOWN
Requires-Dist: OctoPrint
Requires-Dist: prometheus-client
